[
    {
        "title": "Is Typescript bad!?",
        "author": "Elisa",
        "description": "Typescript ist Katastrophe! Zuviel Overhead!",
        "likes": 17,
        "dislikes": 3,
        "image": "https://images.unsplash.com/photo-1534496070640-3252fafd6d65?crop=entropy&cs=tinysrgb&fit=crop&fm=jpg&h=150&ixid=MnwxfDB8MXxyYW5kb218MHx8bmF0dXJlLDF8fHx8fHwxNjU5OTY1NDAz&ixlib=rb-1.2.1&q=80&utm_campaign=api-credit&utm_medium=referral&utm_source=unsplash_source&w=150"
    },
    {
        "title": "Is Backend bad!?",
        "author": "Edward",
        "description": "blub blub blub",
        "likes": 17,
        "dislikes": 3,
        "image": "https://images.unsplash.com/photo-1466133633688-187f0b492390?crop=entropy&cs=tinysrgb&fit=crop&fm=jpg&h=150&ixid=MnwxfDB8MXxyYW5kb218MHx8bmF0dXJlLDB8fHx8fHwxNjU5OTY1MzYw&ixlib=rb-1.2.1&q=80&utm_campaign=api-credit&utm_medium=referral&utm_source=unsplash_source&w=150"
    },
    {
        "title": "Am I the admin!?",
        "author": "Gael",
        "description": "bla bla bla!",
        "likes": 17,
        "dislikes": 3,
        "image": "https://images.unsplash.com/photo-1527606229028-1b50291b25e4?crop=entropy&cs=tinysrgb&fit=crop&fm=jpg&h=150&ixid=MnwxfDB8MXxyYW5kb218MHx8bmF0dXJlLDJ8fHx8fHwxNjU5OTY1NDA1&ixlib=rb-1.2.1&q=80&utm_campaign=api-credit&utm_medium=referral&utm_source=unsplash_source&w=150"
    }
]